{
  "moldes": [
    {
      "id": "mdy12grv0kmohdct13z",
      "mantenimientoProximo": "",
      "numeroActivo": "4444",
      "numeroEquipo": "555",
      "modelo": "Llanera",
      "estacion": "1",
      "talla": "32",
      "ubicacion": "Maquina WT01",
      "estado": "Rechazado por calidad",
      "defecto": "BURS-BURB.(PVC) SUELA",
      "observaciones": "",
      "fechaCreacion": "2025-08-05T04:17:05.135Z",
      "creadoPor": "Administrador Sistema",
      "ultimaModificacion": "2025-08-05T05:17:48.929Z",
      "ultimoModificadoPor": "Administrador Sistema",
      "hojaVida": [
        {
          "fecha": "2025-08-05T04:17:05.136Z",
          "observacion": "Molde creado en el sistema",
          "ubicacion": "Maquina WT01",
          "estado": "Disponible",
          "usuario": "Administrador Sistema",
          "usuarioRole": "admin"
        },
        {
          "fecha": "2025-08-05T05:17:48.929Z",
          "observacion": "Cambio de estado a: Rechazado por calidad, Defecto: BURS-BURB.(PVC) SUELA",
          "ubicacion": "Maquina WT01",
          "estado": "Rechazado por calidad",
          "defecto": "BURS-BURB.(PVC) SUELA",
          "usuario": "Administrador Sistema",
          "usuarioRole": "admin"
        }
      ]
    },
    {
      "id": "mdy1ej4vnosg2lv63mk",
      "mantenimientoProximo": "",
      "numeroActivo": "567",
      "numeroEquipo": "678",
      "modelo": "Llanera",
      "estacion": "4",
      "talla": "48",
      "ubicacion": "Maquina WT01",
      "estado": "Disponible",
      "defecto": "",
      "observaciones": "",
      "fechaCreacion": "2025-08-05T04:26:28.063Z",
      "creadoPor": "Administrador Sistema",
      "ultimaModificacion": "2025-08-05T04:26:28.063Z",
      "ultimoModificadoPor": "Administrador Sistema",
      "hojaVida": [
        {
          "fecha": "2025-08-05T04:26:28.063Z",
          "observacion": "Molde creado en el sistema",
          "ubicacion": "Maquina WT01",
          "estado": "Disponible",
          "usuario": "Administrador Sistema",
          "usuarioRole": "admin"
        }
      ]
    }
  ],
  "lastUpdate": "2025-08-05T05:17:57.282Z",
  "version": "1.0"
}